pythontail/__init__.py
pythontail/pythontail.py
pythontail-0.9.dist-info/LICENSE.md
pythontail-0.9.dist-info/METADATA
pythontail-0.9.dist-info/WHEEL
pythontail-0.9.dist-info/top_level.txt
pythontail-0.9.dist-info/RECORD
