Metadata-Version: 2.1
Name: pythontail
Version: 0.9
Summary: a unix tail implementation in python
Home-page: https://github.com/natanaelfneto/pythontail
Author: natanaelfneto
Author-email: natanaelfneto@outlook.com
Classifier: Programming Language :: Python :: 3
Classifier: License :: OSI Approved :: MIT License
Classifier: Operating System :: OS Independent
License-File: LICENSE.md
